Workbook

Sheet 00_README
A1: Polar Lounge — Finance (P&L + Balance Sheet)
A3: 你要做嘅事（淨係呢樣）
A4: 1. 員工每日喺 Polar Order 埋數（關枱 / Claims / Cash Tilt）→ 撳 Sync to Google Sheet
A5: 2. 你每月／每星期入返銀行流水去「Bank_Entries」黃色格（日期、memo、金額、Nature）
A6: 3. 睇「P&L_Monthly」「Balance_Sheet」「KPI」——全部自動計
A8: 自動化邊度嚟
A9: Daily_Sales ← Polar Order 自動寫入（唔好人手改數字欄）
A10: P&L / Balance Sheet / KPI ← 公式由 Daily_Sales + Bank_Entries 抽出
A11: 舊「Polar Lounge CWB」保留做 archive，唔使再每月開新 tab
A13: Tabs
A14: 00_README | B14: 說明（本頁）
A15: Chart_of_Accounts | B15: 科目表（Nature / account code）
A16: Daily_Sales | B16: 每日埋數（系統 sync）
A17: Bank_Entries | B17: 銀行流水（你入）
A18: P&L_Monthly | B18: 每月損益表
A19: Balance_Sheet | B19: 資產負債表
A20: KPI | B20: 銷售／人工／expense 比率
A22: FY note: 報表以「日曆月」為單位（1–12 月）。開業／partners meeting 用 KPI + 當月 P&L。

Sheet Setup
A1: Setup checklist
A3: 1. Open this file with Google Sheets (File → Save as Google Sheets if still .xlsx)
A4: 2. Share with Polar Order service account as Editor + cwbpolar@gmail.com
A5: 3. Render POLAR_DAILY_SALES_SHEET_ID = this spreadsheet id (from URL)
A6: 4. POLAR_DAILY_SALES_WORKSHEET = Daily_Sales
A7: 5. POLAR_GSPREAD_KEY = service account JSON
A8: 6. You only maintain Bank_Entries (yellow cells)
A9: 7. Temporary Daily_Sales sheet (until step 3): 1GBFYoOa6oBSTono0b6qy8qX6mKQSbOsnaoWTzP-LiIY
A10: 8. Old Polar Lounge CWB stays as historical archive

Sheet Chart_of_Accounts
A1: Chart of Accounts
A2: Bank_Entries 嘅 Nature 必須用呢度嘅名稱（下拉），先會入到 P&L / BS。
A4: account_code | B4: nature | C4: type | D4: pl_section | E4: bs_section | F4: notes | H4: Nature list (for dropdown)
A5: 1000 | B5: HSBC SA | C5: Asset | E5: Current assets | F5: Savings | H5: HSBC SA
A6: 1010 | B6: HSBC CA | C6: Asset | E6: Current assets | F6: Current account | H6: HSBC CA
A7: 1100 | B7: Cash on hand | C7: Asset | E7: Current assets | F7: Till / float（參考 Cash Tilt） | H7: Cash on hand
A8: 1200 | B8: Deposits held | C8: Asset | E8: Non-current assets | F8: 租約／水電按金 | H8: Deposits held
A9: 3000 | B9: Partner capital | C9: Equity | E9: Equity | F9: 開業資本 | H9: Partner capital
A10: 3100 | B10: Partner drawings | C10: Equity | E10: Equity | F10: 股東提取 | H10: Partner drawings
A11: 3200 | B11: Partner cash in | C11: Equity | E11: Equity | F11: 股東注資（銀行入數） | H11: Partner cash in
A12: 4000 | B12: Sales | C12: Revenue | D12: Sales | F12: 銀行入數標 Sales；日銷售亦由 Daily_Sales 計 | H12: Sales
A13: 5000 | B13: Drink / Alcohol | C13: COGS | D13: COGS | F13: 酒水採購 | H13: Drink / Alcohol
A14: 5010 | B14: Shisha stock | C14: COGS | D14: COGS | F14: 水煙原料 | H14: Shisha stock
A15: 5020 | B15: Nuts / snacks | C15: COGS | D15: COGS | F15: 小食 | H15: Nuts / snacks
A16: 5030 | B16: Wine cost | C16: COGS | D16: COGS | F16: 葡萄酒進貨 | H16: Wine cost
A17: 5090 | B17: Other COGS | C17: COGS | D17: COGS | F17: 其他進貨 | H17: Other COGS
A18: 6000 | B18: Rent | C18: Expense | D18: Operating expenses | H18: Rent
A19: 6010 | B19: Management fee | C19: Expense | D19: Operating expenses | H19: Management fee
A20: 6020 | B20: Rates (差餉) | C20: Expense | D20: Operating expenses | H20: Rates (差餉)
A21: 6100 | B21: Wages | C21: Expense | D21: Staff costs | F21: 人工／外勞 | H21: Wages
A22: 6200 | B22: Electricity | C22: Expense | D22: Utilities | F22: HKE | H22: Electricity
A23: 6210 | B23: Water | C23: Expense | D23: Utilities | H23: Water
A24: 6220 | B24: Internet | C24: Expense | D24: Utilities | F24: HKBN | H24: Internet
A25: 6300 | B25: Marketing fee | C25: Expense | D25: Operating expenses | H25: Marketing fee
A26: 6400 | B26: Claim | C26: Expense | D26: Claims | F26: 員工墊支報銷（銀行／現金） | H26: Claim
A27: 6500 | B27: Repairs & maintenance | C27: Expense | D27: Operating expenses | H27: Repairs & maintenance
A28: 6900 | B28: Miscellaneous | C28: Expense | D28: Operating expenses | H28: Miscellaneous
A29: 6910 | B29: Membership / BNI | C29: Expense | D29: Operating expenses | H29: Membership / BNI

Sheet Daily_Sales
A1: Daily_Sales — auto from Polar Order
A2: 唔好人手改呢啲數字。系統 Sync 會按 business_date upsert。Cash Tilt／Claim 喺 Order Reports 入完先 sync。
A3: Bridge: until Render points Sync at THIS workbook, pull live rows with (Google Sheets only): =IMPORTRANGE("1GBFYoOa6oBSTono0b6qy8qX6mKQSbOsnaoWTzP-LiIY","Daily_Sales!A2:N") in A5 — or keep Sync writing here after you convert this file to Google Sheets. | P3: Helpers (auto)
A4: business_date | B4: Cash | C4: Visa | D4: Master | E4: AE | F4: Alipay | G4: UnionPay | H4: WeChat pay | I4: Deposit | J4: Claim | K4: Daily Sales | L4: Cash Tilt | M4: Monthly Total | N4: synced_at | P4: Report year | Q4: 2026
P5: Report month (1-12) | Q5: 10
P6: Month sales (Daily Sales col) | Q6: =SUMIFS(K:K,A:A,">="&TEXT(DATE(Q4,Q5,1),"yyyy-mm-dd"),A:A,"<"&TEXT(DATE(Q4,Q5+1,1),"yyyy-mm-dd"))
P7: Month claims (sheet) | Q7: =SUMIFS(J:J,A:A,">="&TEXT(DATE(Q4,Q5,1),"yyyy-mm-dd"),A:A,"<"&TEXT(DATE(Q4,Q5+1,1),"yyyy-mm-dd"))
P8: Month cash tilt (last nonblank approx = sum) | Q8: =SUMIFS(L:L,A:A,">="&TEXT(DATE(Q4,Q5,1),"yyyy-mm-dd"),A:A,"<"&TEXT(DATE(Q4,Q5+1,1),"yyyy-mm-dd"))
P9: YTD sales | Q9: =SUMIFS(K:K,A:A,">="&TEXT(DATE(Q4,1,1),"yyyy-mm-dd"),A:A,"<"&TEXT(DATE(Q4+1,1,1),"yyyy-mm-dd"))
P10: Latest Cash Tilt | Q10: =IFERROR(LOOKUP(2,1/(A5:A1000<>""),L5:L1000),0)

Sheet Bank_Entries
A1: Bank_Entries — 你入（黃色格）
A2: 由 HSBC / 銀行 app 抄過嚟。金額：入數用正數，出數用負數。SA／CA 分兩欄填其中一欄即可。Nature 用下拉。
A3: Partner cash in / Partner drawings / Sales 等 Nature 會自動入 P&L 或 Equity。
K4: Bank helpers
A5: date | B5: memo | C5: chq_no | D5: hsbc_sa | E5: hsbc_ca | F5: nature | G5: account_code | H5: linked_sales_date | I5: notes | K5: HSBC SA balance (sum) | L5: =SUM(D6:D500)
G6: =IF(F6="","",IFERROR(INDEX(Chart_of_Accounts!$A$5:$A$30,MATCH(F6,Chart_of_Accounts!$B$5:$B$30,0)),"")) | K6: HSBC CA balance (sum) | L6: =SUM(E6:E500)
G7: =IF(F7="","",IFERROR(INDEX(Chart_of_Accounts!$A$5:$A$30,MATCH(F7,Chart_of_Accounts!$B$5:$B$30,0)),"")) | K7: Total bank | L7: =L5+L6
G8: =IF(F8="","",IFERROR(INDEX(Chart_of_Accounts!$A$5:$A$30,MATCH(F8,Chart_of_Accounts!$B$5:$B$30,0)),"")) | K8: Selected month bank outflows (expenses/cogs) | L8: (see P&L)
G9: =IF(F9="","",IFERROR(INDEX(Chart_of_Accounts!$A$5:$A$30,MATCH(F9,Chart_of_Accounts!$B$5:$B$30,0)),""))
G10: =IF(F10="","",IFERROR(INDEX(Chart_of_Accounts!$A$5:$A$30,MATCH(F10,Chart_of_Accounts!$B$5:$B$30,0)),""))
G11: =IF(F11="","",IFERROR(INDEX(Chart_of_Accounts!$A$5:$A$30,MATCH(F11,Chart_of_Accounts!$B$5:$B$30,0)),""))
G12: =IF(F12="","",IFERROR(INDEX(Chart_of_Accounts!$A$5:$A$30,MATCH(F12,Chart_of_Accounts!$B$5:$B$30,0)),""))
G13: =IF(F13="","",IFERROR(INDEX(Chart_of_Accounts!$A$5:$A$30,MATCH(F13,Chart_of_Accounts!$B$5:$B$30,0)),""))
G14: =IF(F14="","",IFERROR(INDEX(Chart_of_Accounts!$A$5:$A$30,MATCH(F14,Chart_of_Accounts!$B$5:$B$30,0)),""))
G15: =IF(F15="","",IFERROR(INDEX(Chart_of_Accounts!$A$5:$A$30,MATCH(F15,Chart_of_Accounts!$B$5:$B$30,0)),""))
G16: =IF(F16="","",IFERROR(INDEX(Chart_of_Accounts!$A$5:$A$30,MATCH(F16,Chart_of_Accounts!$B$5:$B$30,0)),""))
G17: =IF(F17="","",IFERROR(INDEX(Chart_of_Accounts!$A$5:$A$30,MATCH(F17,Chart_of_Accounts!$B$5:$B$30,0)),""))
G18: =IF(F18="","",IFERROR(INDEX(Chart_of_Accounts!$A$5:$A$30,MATCH(F18,Chart_of_Accounts!$B$5:$B$30,0)),""))
G19: =IF(F19="","",IFERROR(INDEX(Chart_of_Accounts!$A$5:$A$30,MATCH(F19,Chart_of_Accounts!$B$5:$B$30,0)),""))
G20: =IF(F20="","",IFERROR(INDEX(Chart_of_Accounts!$A$5:$A$30,MATCH(F20,Chart_of_Accounts!$B$5:$B$30,0)),""))
... G79: =IF(F79="","",IFERROR(INDEX(Chart_of_Accounts!$A$5:$A$30,MATCH(F79,Chart_of_Accounts!$B$5:$B$30,0)),""))

Sheet P&L_Monthly
A1: Profit & Loss — Monthly
A2: Year / Month 喺黃色格改。Sales 優先用 Daily_Sales；銀行標 Sales 只作對帳參考。
A4: Year | B4: 2026 | C4: Period start | D4: =DATE(B4,B5,1)
A5: Month | B5: 10 | C5: Period end | D5: =EOMONTH(D4,0)
A7: Income
A8: Sales (from Daily_Sales) | B8: =SUMIFS(Daily_Sales!K:K,Daily_Sales!A:A,">="&TEXT($D$4,"yyyy-mm-dd"),Daily_Sales!A:A,"<="&TEXT($D$5,"yyyy-mm-dd"))
A9: Bank tagged Sales (recon only) | B9: =SUMIFS(Bank_Entries!D:D,Bank_Entries!F:F,"Sales",Bank_Entries!A:A,">="&$D$4,Bank_Entries!A:A,"<="&$D$5)+SUMIFS(Bank_Entries!E:E,Bank_Entries!F:F,"Sales",Bank_Entries!A:A,">="&$D$4,Bank_Entries!A:A,"<="&$D$5)
A10: Net sales (uses Daily_Sales) | B10: =B8
A12: Cost of goods sold
A13: Drink / Alcohol | B13: =ABS(SUMIFS(Bank_Entries!D:D,Bank_Entries!F:F,A13,Bank_Entries!A:A,">="&$D$4,Bank_Entries!A:A,"<="&$D$5)+SUMIFS(Bank_Entries!E:E,Bank_Entries!F:F,A13,Bank_Entries!A:A,">="&$D$4,Bank_Entries!A:A,"<="&$D$5))
A14: Shisha stock | B14: =ABS(SUMIFS(Bank_Entries!D:D,Bank_Entries!F:F,A14,Bank_Entries!A:A,">="&$D$4,Bank_Entries!A:A,"<="&$D$5)+SUMIFS(Bank_Entries!E:E,Bank_Entries!F:F,A14,Bank_Entries!A:A,">="&$D$4,Bank_Entries!A:A,"<="&$D$5))
A15: Nuts / snacks | B15: =ABS(SUMIFS(Bank_Entries!D:D,Bank_Entries!F:F,A15,Bank_Entries!A:A,">="&$D$4,Bank_Entries!A:A,"<="&$D$5)+SUMIFS(Bank_Entries!E:E,Bank_Entries!F:F,A15,Bank_Entries!A:A,">="&$D$4,Bank_Entries!A:A,"<="&$D$5))
A16: Wine cost | B16: =ABS(SUMIFS(Bank_Entries!D:D,Bank_Entries!F:F,A16,Bank_Entries!A:A,">="&$D$4,Bank_Entries!A:A,"<="&$D$5)+SUMIFS(Bank_Entries!E:E,Bank_Entries!F:F,A16,Bank_Entries!A:A,">="&$D$4,Bank_Entries!A:A,"<="&$D$5))
A17: Other COGS | B17: =ABS(SUMIFS(Bank_Entries!D:D,Bank_Entries!F:F,A17,Bank_Entries!A:A,">="&$D$4,Bank_Entries!A:A,"<="&$D$5)+SUMIFS(Bank_Entries!E:E,Bank_Entries!F:F,A17,Bank_Entries!A:A,">="&$D$4,Bank_Entries!A:A,"<="&$D$5))
A18: Total COGS | B18: =SUM(B13:B17)
A20: Gross profit | B20: =B10-B18
A22: Operating expenses
A23: Rent | B23: =ABS(SUMIFS(Bank_Entries!D:D,Bank_Entries!F:F,A23,Bank_Entries!A:A,">="&$D$4,Bank_Entries!A:A,"<="&$D$5)+SUMIFS(Bank_Entries!E:E,Bank_Entries!F:F,A23,Bank_Entries!A:A,">="&$D$4,Bank_Entries!A:A,"<="&$D$5))
A24: Management fee | B24: =ABS(SUMIFS(Bank_Entries!D:D,Bank_Entries!F:F,A24,Bank_Entries!A:A,">="&$D$4,Bank_Entries!A:A,"<="&$D$5)+SUMIFS(Bank_Entries!E:E,Bank_Entries!F:F,A24,Bank_Entries!A:A,">="&$D$4,Bank_Entries!A:A,"<="&$D$5))
A25: Rates (差餉) | B25: =ABS(SUMIFS(Bank_Entries!D:D,Bank_Entries!F:F,A25,Bank_Entries!A:A,">="&$D$4,Bank_Entries!A:A,"<="&$D$5)+SUMIFS(Bank_Entries!E:E,Bank_Entries!F:F,A25,Bank_Entries!A:A,">="&$D$4,Bank_Entries!A:A,"<="&$D$5))
A26: Wages | B26: =ABS(SUMIFS(Bank_Entries!D:D,Bank_Entries!F:F,A26,Bank_Entries!A:A,">="&$D$4,Bank_Entries!A:A,"<="&$D$5)+SUMIFS(Bank_Entries!E:E,Bank_Entries!F:F,A26,Bank_Entries!A:A,">="&$D$4,Bank_Entries!A:A,"<="&$D$5))
A27: Electricity | B27: =ABS(SUMIFS(Bank_Entries!D:D,Bank_Entries!F:F,A27,Bank_Entries!A:A,">="&$D$4,Bank_Entries!A:A,"<="&$D$5)+SUMIFS(Bank_Entries!E:E,Bank_Entries!F:F,A27,Bank_Entries!A:A,">="&$D$4,Bank_Entries!A:A,"<="&$D$5))
A28: Water | B28: =ABS(SUMIFS(Bank_Entries!D:D,Bank_Entries!F:F,A28,Bank_Entries!A:A,">="&$D$4,Bank_Entries!A:A,"<="&$D$5)+SUMIFS(Bank_Entries!E:E,Bank_Entries!F:F,A28,Bank_Entries!A:A,">="&$D$4,Bank_Entries!A:A,"<="&$D$5))
A29: Internet | B29: =ABS(SUMIFS(Bank_Entries!D:D,Bank_Entries!F:F,A29,Bank_Entries!A:A,">="&$D$4,Bank_Entries!A:A,"<="&$D$5)+SUMIFS(Bank_Entries!E:E,Bank_Entries!F:F,A29,Bank_Entries!A:A,">="&$D$4,Bank_Entries!A:A,"<="&$D$5))
A30: Marketing fee | B30: =ABS(SUMIFS(Bank_Entries!D:D,Bank_Entries!F:F,A30,Bank_Entries!A:A,">="&$D$4,Bank_Entries!A:A,"<="&$D$5)+SUMIFS(Bank_Entries!E:E,Bank_Entries!F:F,A30,Bank_Entries!A:A,">="&$D$4,Bank_Entries!A:A,"<="&$D$5))
A31: Claim | B31: =ABS(SUMIFS(Bank_Entries!D:D,Bank_Entries!F:F,A31,Bank_Entries!A:A,">="&$D$4,Bank_Entries!A:A,"<="&$D$5)+SUMIFS(Bank_Entries!E:E,Bank_Entries!F:F,A31,Bank_Entries!A:A,">="&$D$4,Bank_Entries!A:A,"<="&$D$5))
A32: Repairs & maintenance | B32: =ABS(SUMIFS(Bank_Entries!D:D,Bank_Entries!F:F,A32,Bank_Entries!A:A,">="&$D$4,Bank_Entries!A:A,"<="&$D$5)+SUMIFS(Bank_Entries!E:E,Bank_Entries!F:F,A32,Bank_Entries!A:A,">="&$D$4,Bank_Entries!A:A,"<="&$D$5))
A33: Miscellaneous | B33: =ABS(SUMIFS(Bank_Entries!D:D,Bank_Entries!F:F,A33,Bank_Entries!A:A,">="&$D$4,Bank_Entries!A:A,"<="&$D$5)+SUMIFS(Bank_Entries!E:E,Bank_Entries!F:F,A33,Bank_Entries!A:A,">="&$D$4,Bank_Entries!A:A,"<="&$D$5))
A34: Membership / BNI | B34: =ABS(SUMIFS(Bank_Entries!D:D,Bank_Entries!F:F,A34,Bank_Entries!A:A,">="&$D$4,Bank_Entries!A:A,"<="&$D$5)+SUMIFS(Bank_Entries!E:E,Bank_Entries!F:F,A34,Bank_Entries!A:A,">="&$D$4,Bank_Entries!A:A,"<="&$D$5))
A35: Claims recorded in Order (Daily_Sales) | B35: =SUMIFS(Daily_Sales!J:J,Daily_Sales!A:A,">="&TEXT($D$4,"yyyy-mm-dd"),Daily_Sales!A:A,"<="&TEXT($D$5,"yyyy-mm-dd"))
A36: Total operating expenses | B36: =SUM(B23:B35)
A38: Net profit / (loss) | B38: =B20-B36
A40: Ratios
A41: Wages / Net sales | B41: =IF(B10=0,0,ABS(SUMIFS(Bank_Entries!D:D,Bank_Entries!F:F,"Wages",Bank_Entries!A:A,">="&$D$4,Bank_Entries!A:A,"<="&$D$5)+SUMIFS(Bank_Entries!E:E,Bank_Entries!F:F,"Wages",Bank_Entries!A:A,">="&$D$4,Bank_Entries!A:A,"<="&$D$5))/B10)
A42: Total expenses / Net sales | B42: =IF(B10=0,0,B36/B10)
A43: Net margin | B43: =IF(B10=0,0,B38/B10)

Sheet Balance_Sheet
A1: Balance Sheet
A2: As-of 用黃色格。銀行結餘 = Bank_Entries 累計；Cash on hand 用 Daily_Sales 最近 Cash Tilt 作 control。
A4: As of date | B4: 46322
A6: Assets
A7: HSBC SA | B7: =SUMIF(Bank_Entries!A:A,"<="&$B$4,Bank_Entries!D:D)
A8: HSBC CA | B8: =SUMIF(Bank_Entries!A:A,"<="&$B$4,Bank_Entries!E:E)
A9: Cash on hand (Cash Tilt control) | B9: =Daily_Sales!Q10
A10: Deposits held (bank Nature) | B10: =ABS(SUMIFS(Bank_Entries!D:D,Bank_Entries!F:F,"Deposits held",Bank_Entries!A:A,"<="&$B$4)+SUMIFS(Bank_Entries!E:E,Bank_Entries!F:F,"Deposits held",Bank_Entries!A:A,"<="&$B$4))
A11: Total assets | B11: =B7+B8+B9+B10
A13: Equity
A14: Partner capital | B14: =SUMIFS(Bank_Entries!D:D,Bank_Entries!F:F,"Partner capital",Bank_Entries!A:A,"<="&$B$4)+SUMIFS(Bank_Entries!E:E,Bank_Entries!F:F,"Partner capital",Bank_Entries!A:A,"<="&$B$4)
A15: Partner cash in | B15: =SUMIFS(Bank_Entries!D:D,Bank_Entries!F:F,"Partner cash in",Bank_Entries!A:A,"<="&$B$4)+SUMIFS(Bank_Entries!E:E,Bank_Entries!F:F,"Partner cash in",Bank_Entries!A:A,"<="&$B$4)
A16: Partner drawings | B16: =ABS(SUMIFS(Bank_Entries!D:D,Bank_Entries!F:F,"Partner drawings",Bank_Entries!A:A,"<="&$B$4)+SUMIFS(Bank_Entries!E:E,Bank_Entries!F:F,"Partner drawings",Bank_Entries!A:A,"<="&$B$4))
A17: Retained earnings (plug to balance) | B17: =B11-(B14+B15-B16)
A18: Total equity | B18: =B14+B15-B16+B17
A20: Check (Assets − Equity should be 0) | B20: =B11-B18
A22: Note: Retained earnings is a balancing figure until full journal history is loaded. Net profit from P&L feeds partners meetings; bank history builds the true equity over time.

Sheet KPI
A1: KPI Dashboard
A2: 跟 P&L_Monthly 同一個 Year/Month（改 P&L 頁黃色格即可；呢頁讀返）。
A4: Year | B4: =P&L_Monthly!B4
A5: Month | B5: =P&L_Monthly!B5
A7: Net sales | B7: =P&L_Monthly!B10
A8: Gross profit | B8: =P&L_Monthly!B20
A9: Net profit | B9: =P&L_Monthly!B38
A10: Claims (Order) | B10: =P&L_Monthly!B35
A11: Wages / sales | B11: =IF(B7=0,0,ABS(SUMIFS(Bank_Entries!D:D,Bank_Entries!F:F,"Wages",Bank_Entries!A:A,">="&P&L_Monthly!D4,Bank_Entries!A:A,"<="&P&L_Monthly!D5)+SUMIFS(Bank_Entries!E:E,Bank_Entries!F:F,"Wages",Bank_Entries!A:A,">="&P&L_Monthly!D4,Bank_Entries!A:A,"<="&P&L_Monthly!D5))/B7)
A12: Expense / sales | B12: =IF(B7=0,0,P&L_Monthly!B36/B7)
A13: Bank total (to date) | B13: =Bank_Entries!L7
A14: YTD Daily Sales | B14: =Daily_Sales!Q9
A16: Partners meeting: 抄 Net sales / Gross profit / Net profit / Wages% / Expense% 去 Canva deck。
